sc2ts/__init__.py
sc2ts/__main__.py
sc2ts/_version.py
sc2ts/alignments.py
sc2ts/buildtree.py
sc2ts/cli.py
sc2ts/core.py
sc2ts/inference.py
sc2ts/lineages.py
sc2ts/local_tree.py
sc2ts/metadata.py
sc2ts/nextstrain.py
sc2ts/utils.py
sc2ts/data/annotation.csv
sc2ts/data/problematic_sites.txt
sc2ts/data/reference.fasta
sc2ts-0.0.3.dist-info/LICENSE
sc2ts-0.0.3.dist-info/METADATA
sc2ts-0.0.3.dist-info/WHEEL
sc2ts-0.0.3.dist-info/top_level.txt
sc2ts-0.0.3.dist-info/RECORD
