Metadata-Version: 2.1
Name: sc2ts
Version: 0.0.3
Summary: Infer a succinct tree sequence from SARS-CoV-2 sequence alignments
Author: Jerome Kelleher
Author-email: jerome.kelleher@bdi.ox.ac.uk
License: MIT
Requires-Python: >=3.7
License-File: LICENSE
Requires-Dist: tskit (>=0.5.3)
Requires-Dist: tszip
Requires-Dist: tsinfer (>=0.3.0)
Requires-Dist: setuptools (>=41.2)
Requires-Dist: numba
Requires-Dist: pandas
Requires-Dist: tqdm
Requires-Dist: pyfaidx
Requires-Dist: scipy
Requires-Dist: click
Provides-Extra: analysis
Requires-Dist: matplotlib ; extra == 'analysis'
Requires-Dist: scikit-learn ; extra == 'analysis'
Requires-Dist: pandas ; extra == 'analysis'
Requires-Dist: IPython ; extra == 'analysis'
Requires-Dist: networkx ; extra == 'analysis'
Provides-Extra: setup_requires
Requires-Dist: setuptools (>=41.2) ; extra == 'setup_requires'
Requires-Dist: setuptools-scm ; extra == 'setup_requires'
